COPYING
MANIFEST.in
setup.py
binplist/__init__.py
binplist/binplist.py
binplist.egg-info/PKG-INFO
binplist.egg-info/SOURCES.txt
binplist.egg-info/dependency_links.txt
binplist.egg-info/requires.txt
binplist.egg-info/top_level.txt
dpkg/binplist.docs
dpkg/changelog
dpkg/compat
dpkg/control
dpkg/copyright
dpkg/rules
scripts/plist.py
tests/__init__.py
tests/binplist_test.py