Metadata-Version: 1.0
Name: binplist
Version: 0.1.4
Summary: A binary plist parser
Home-page: http://code.google.com/p/binplist
Author: Jordi Sanchez
Author-email: binplist.feedback@gmail.com
License: Apache Software License
Platform: UNKNOWN
